LICENSE
csc_recorder/APIHandler.py
csc_recorder/CSC/templates/CreatePackage.xml
csc_recorder/CSCRecorder.py
csc_recorder/__init__.py
csc_recorder/constants.py
csc_recorder-1.4.1.dist-info/LICENSE
csc_recorder-1.4.1.dist-info/WHEEL
csc_recorder-1.4.1.dist-info/METADATA
csc_recorder-1.4.1.dist-info/RECORD
